{
  "b": 209,
  "disableInputWhenNotFocused": true,
  "mangledName": "upgrade",
  "name": "upgrade",
  "r": 209,
  "standardSortMethod": true,
  "stopSoundsOnStartup": false,
  "title": "",
  "v": 209,
  "uiSettings": {
    "grid": false,
    "gridType": "rectangular",
    "gridWidth": 32,
    "gridHeight": 32,
    "gridOffsetX": 0,
    "gridOffsetY": 0,
    "gridColor": 10401023,
    "gridAlpha": 0.8,
    "snap": false,
    "zoomFactor": 0.5653158055126308,
    "windowMask": false
  },
  "objectsGroups": [],
  "variables": [
    {
      "name": "CurrencyTemp",
      "type": "number",
      "value": 0
    },
    {
      "name": "TempUpgrades",
      "type": "string",
      "value": "0"
    },
    {
      "name": "LastUpdatedCurrency",
      "type": "number",
      "value": -1
    }
  ],
  "instances": [
    {
      "angle": 0,
      "customSize": true,
      "depth": 0.9986052998605301,
      "height": 95,
      "keepRatio": true,
      "layer": "",
      "name": "Title",
      "persistentUuid": "abe78606-46a9-4f19-96f6-aa5adaed9919",
      "width": 716,
      "x": 2,
      "y": 102,
      "zOrder": 3,
      "numberProperties": [],
      "stringProperties": [],
      "initialVariables": []
    },
    {
      "angle": 0,
      "customSize": true,
      "depth": 60,
      "height": 80,
      "keepRatio": true,
      "layer": "",
      "name": "ReadyButton",
      "persistentUuid": "e691efbe-0aeb-45f8-b26c-345cb032ddf5",
      "width": 240,
      "x": 245,
      "y": 1050,
      "zOrder": 2,
      "numberProperties": [],
      "stringProperties": [],
      "initialVariables": []
    },
    {
      "angle": 0,
      "customSize": true,
      "depth": 48,
      "height": 80,
      "layer": "",
      "name": "DebugAddMoney",
      "persistentUuid": "e5c6670e-b397-4958-aab8-9b39306f244a",
      "width": 80,
      "x": 40,
      "y": 1160,
      "zOrder": 3,
      "numberProperties": [],
      "stringProperties": [],
      "initialVariables": []
    },
    {
      "angle": 0,
      "customSize": true,
      "depth": 0.8163265306122448,
      "height": 40,
      "layer": "",
      "name": "CurrencyDisplay",
      "persistentUuid": "9894aed9-f5fe-4307-b238-e3f1843e314e",
      "width": 280,
      "x": 202,
      "y": 1180,
      "zOrder": 4,
      "numberProperties": [],
      "stringProperties": [],
      "initialVariables": []
    },
    {
      "angle": 0,
      "customSize": true,
      "depth": 48,
      "height": 80,
      "layer": "",
      "name": "DebugRemoveMoney",
      "persistentUuid": "51d158ea-cf4f-4394-8654-cb2f9ed6f3f2",
      "width": 80,
      "x": 600,
      "y": 1160,
      "zOrder": 5,
      "numberProperties": [],
      "stringProperties": [],
      "initialVariables": []
    },
    {
      "angle": 0,
      "customSize": true,
      "depth": 1.044776119402985,
      "height": 70,
      "keepRatio": true,
      "layer": "",
      "name": "UpgradeIcon",
      "persistentUuid": "f7c971ee-7612-439d-8e4a-224c8df6cfea",
      "width": 70,
      "x": 25,
      "y": 178,
      "zOrder": 6,
      "numberProperties": [],
      "stringProperties": [],
      "initialVariables": [
        {
          "name": "Upgrade",
          "type": "string",
          "value": "ChromaSpread"
        }
      ]
    },
    {
      "angle": 0,
      "customSize": false,
      "height": 0,
      "keepRatio": true,
      "layer": "",
      "name": "UpgradeName",
      "persistentUuid": "2193222e-5e74-4b07-983b-68568d819025",
      "width": 0,
      "x": 219,
      "y": 204,
      "zOrder": 8,
      "numberProperties": [],
      "stringProperties": [],
      "initialVariables": []
    },
    {
      "angle": 0,
      "customSize": false,
      "height": 0,
      "keepRatio": true,
      "layer": "",
      "name": "UpgradeLevel",
      "persistentUuid": "cda8dfca-c25d-4ead-93a2-d125eba39c0d",
      "width": 0,
      "x": 130,
      "y": 204,
      "zOrder": 9,
      "numberProperties": [],
      "stringProperties": [],
      "initialVariables": []
    },
    {
      "angle": 0,
      "customSize": false,
      "height": 0,
      "keepRatio": true,
      "layer": "",
      "name": "UpgradePrice",
      "persistentUuid": "dea86a04-3693-4b34-8125-c19d68ccbd32",
      "width": 0,
      "x": 617,
      "y": 204,
      "zOrder": 10,
      "numberProperties": [],
      "stringProperties": [],
      "initialVariables": []
    },
    {
      "angle": 0,
      "customSize": true,
      "depth": 1.044776119402985,
      "height": 70,
      "keepRatio": true,
      "layer": "",
      "name": "UpgradeIcon",
      "persistentUuid": "a1c89113-bacf-41dd-8424-4a4e27d4b70b",
      "width": 70,
      "x": 25,
      "y": 278,
      "zOrder": 6,
      "numberProperties": [],
      "stringProperties": [],
      "initialVariables": []
    },
    {
      "angle": 0,
      "customSize": false,
      "height": 0,
      "keepRatio": true,
      "layer": "",
      "name": "UpgradeName",
      "persistentUuid": "a887a00b-d95b-4f49-860f-60a958862276",
      "width": 0,
      "x": 219,
      "y": 304,
      "zOrder": 8,
      "numberProperties": [],
      "stringProperties": [],
      "initialVariables": [
        {
          "name": "Upgrade",
          "type": "string",
          "value": "DamageRock"
        }
      ]
    },
    {
      "angle": 0,
      "customSize": false,
      "height": 0,
      "keepRatio": true,
      "layer": "",
      "name": "UpgradeLevel",
      "persistentUuid": "8224c9aa-7a77-4faa-9e6f-ee8e31b07c87",
      "width": 0,
      "x": 130,
      "y": 304,
      "zOrder": 9,
      "numberProperties": [],
      "stringProperties": [],
      "initialVariables": [
        {
          "name": "Upgrade",
          "type": "string",
          "value": "DamageRock"
        }
      ]
    },
    {
      "angle": 0,
      "customSize": false,
      "height": 0,
      "keepRatio": true,
      "layer": "",
      "name": "UpgradePrice",
      "persistentUuid": "9d7f1201-a8f3-465c-803f-a935e1a6c8e2",
      "width": 0,
      "x": 617,
      "y": 304,
      "zOrder": 10,
      "numberProperties": [],
      "stringProperties": [],
      "initialVariables": [
        {
          "name": "Upgrade",
          "type": "string",
          "value": "DamageRock"
        }
      ]
    },
    {
      "angle": 0,
      "customSize": true,
      "depth": 1.044776119402985,
      "height": 70,
      "keepRatio": true,
      "layer": "",
      "name": "UpgradeIcon",
      "persistentUuid": "88d5e355-8b68-4dab-a985-4f049f40af59",
      "width": 70,
      "x": 25,
      "y": 382,
      "zOrder": 6,
      "numberProperties": [],
      "stringProperties": [],
      "initialVariables": [
        {
          "name": "Upgrade",
          "type": "string",
          "value": "FireRate"
        }
      ]
    },
    {
      "angle": 0,
      "customSize": false,
      "height": 0,
      "keepRatio": true,
      "layer": "",
      "name": "UpgradeName",
      "persistentUuid": "80b9a04e-fc47-4ce5-9377-71139d2d9504",
      "width": 0,
      "x": 219,
      "y": 408,
      "zOrder": 8,
      "numberProperties": [],
      "stringProperties": [],
      "initialVariables": [
        {
          "name": "Upgrade",
          "type": "string",
          "value": "FireRate"
        }
      ]
    },
    {
      "angle": 0,
      "customSize": false,
      "height": 0,
      "keepRatio": true,
      "layer": "",
      "name": "UpgradeLevel",
      "persistentUuid": "ad975bcf-a075-4b50-aaa4-8313087d7cd3",
      "width": 0,
      "x": 130,
      "y": 408,
      "zOrder": 9,
      "numberProperties": [],
      "stringProperties": [],
      "initialVariables": [
        {
          "name": "Upgrade",
          "type": "string",
          "value": "FireRate"
        }
      ]
    },
    {
      "angle": 0,
      "customSize": false,
      "height": 0,
      "keepRatio": true,
      "layer": "",
      "name": "UpgradePrice",
      "persistentUuid": "40d62eaa-4c27-483f-8be5-3e4a36b221ea",
      "width": 0,
      "x": 617,
      "y": 408,
      "zOrder": 10,
      "numberProperties": [],
      "stringProperties": [],
      "initialVariables": [
        {
          "name": "Upgrade",
          "type": "string",
          "value": "FireRate"
        }
      ]
    },
    {
      "angle": 0,
      "customSize": true,
      "depth": 1.044776119402985,
      "height": 70,
      "keepRatio": true,
      "layer": "",
      "name": "UpgradeIcon",
      "persistentUuid": "59c17980-14b4-41d6-9ff2-3059d5ee44e9",
      "width": 70,
      "x": 25,
      "y": 478,
      "zOrder": 6,
      "numberProperties": [],
      "stringProperties": [],
      "initialVariables": [
        {
          "name": "Upgrade",
          "type": "string",
          "value": "Health"
        }
      ]
    },
    {
      "angle": 0,
      "customSize": false,
      "height": 0,
      "keepRatio": true,
      "layer": "",
      "name": "UpgradeName",
      "persistentUuid": "36181579-6368-4edd-80cf-c2977b2a89c2",
      "width": 0,
      "x": 219,
      "y": 504,
      "zOrder": 8,
      "numberProperties": [],
      "stringProperties": [],
      "initialVariables": [
        {
          "name": "Upgrade",
          "type": "string",
          "value": "Health"
        }
      ]
    },
    {
      "angle": 0,
      "customSize": false,
      "height": 0,
      "keepRatio": true,
      "layer": "",
      "name": "UpgradeLevel",
      "persistentUuid": "43a7e50a-4263-4a80-8680-b7c8773055ff",
      "width": 0,
      "x": 130,
      "y": 504,
      "zOrder": 9,
      "numberProperties": [],
      "stringProperties": [],
      "initialVariables": [
        {
          "name": "Upgrade",
          "type": "string",
          "value": "Health"
        }
      ]
    },
    {
      "angle": 0,
      "customSize": false,
      "height": 0,
      "keepRatio": true,
      "layer": "",
      "name": "UpgradePrice",
      "persistentUuid": "a1b5bad0-2d6e-4bed-8efe-58db06965e54",
      "width": 0,
      "x": 617,
      "y": 504,
      "zOrder": 10,
      "numberProperties": [],
      "stringProperties": [],
      "initialVariables": [
        {
          "name": "Upgrade",
          "type": "string",
          "value": "Health"
        }
      ]
    },
    {
      "angle": 0,
      "customSize": true,
      "depth": 1.044776119402985,
      "height": 70,
      "keepRatio": true,
      "layer": "",
      "name": "UpgradeIcon",
      "persistentUuid": "77a9b983-6d9b-46d9-840b-d1f0b3793bfd",
      "width": 70,
      "x": 25,
      "y": 578,
      "zOrder": 6,
      "numberProperties": [],
      "stringProperties": [],
      "initialVariables": [
        {
          "name": "Upgrade",
          "type": "string",
          "value": "PlayerDamage"
        }
      ]
    },
    {
      "angle": 0,
      "customSize": false,
      "height": 0,
      "keepRatio": true,
      "layer": "",
      "name": "UpgradeName",
      "persistentUuid": "f054c4a1-1b47-4bfc-bfe0-8b98c968c9ab",
      "width": 0,
      "x": 219,
      "y": 604,
      "zOrder": 8,
      "numberProperties": [],
      "stringProperties": [],
      "initialVariables": [
        {
          "name": "Upgrade",
          "type": "string",
          "value": "PlayerDamage"
        }
      ]
    },
    {
      "angle": 0,
      "customSize": false,
      "height": 0,
      "keepRatio": true,
      "layer": "",
      "name": "UpgradeLevel",
      "persistentUuid": "6ab3f9ca-ac0f-42ef-8053-1399093c02e3",
      "width": 0,
      "x": 130,
      "y": 604,
      "zOrder": 9,
      "numberProperties": [],
      "stringProperties": [],
      "initialVariables": [
        {
          "name": "Upgrade",
          "type": "string",
          "value": "PlayerDamage"
        }
      ]
    },
    {
      "angle": 0,
      "customSize": false,
      "height": 0,
      "keepRatio": true,
      "layer": "",
      "name": "UpgradePrice",
      "persistentUuid": "2307223d-7fa6-41d6-8507-bb389372f129",
      "width": 0,
      "x": 617,
      "y": 604,
      "zOrder": 10,
      "numberProperties": [],
      "stringProperties": [],
      "initialVariables": [
        {
          "name": "Upgrade",
          "type": "string",
          "value": "PlayerDamage"
        }
      ]
    },
    {
      "angle": 0,
      "customSize": true,
      "depth": 1.044776119402985,
      "height": 70,
      "keepRatio": true,
      "layer": "",
      "name": "UpgradeIcon",
      "persistentUuid": "19a5169e-a5e3-4a04-b34a-0c5040e44ae2",
      "width": 70,
      "x": 25,
      "y": 678,
      "zOrder": 6,
      "numberProperties": [],
      "stringProperties": [],
      "initialVariables": [
        {
          "name": "Upgrade",
          "type": "string",
          "value": "ProjectileSpeed"
        }
      ]
    },
    {
      "angle": 0,
      "customSize": false,
      "height": 0,
      "keepRatio": true,
      "layer": "",
      "name": "UpgradeName",
      "persistentUuid": "59a1766f-f5e9-4077-b52a-0eca0c28a872",
      "width": 0,
      "x": 219,
      "y": 704,
      "zOrder": 8,
      "numberProperties": [],
      "stringProperties": [],
      "initialVariables": [
        {
          "name": "Upgrade",
          "type": "string",
          "value": "ProjectileSpeed"
        }
      ]
    },
    {
      "angle": 0,
      "customSize": false,
      "height": 0,
      "keepRatio": true,
      "layer": "",
      "name": "UpgradeLevel",
      "persistentUuid": "3d63a0c9-2f12-4860-87a0-a49444ad3998",
      "width": 0,
      "x": 130,
      "y": 704,
      "zOrder": 9,
      "numberProperties": [],
      "stringProperties": [],
      "initialVariables": [
        {
          "name": "Upgrade",
          "type": "string",
          "value": "ProjectileSpeed"
        }
      ]
    },
    {
      "angle": 0,
      "customSize": false,
      "height": 0,
      "keepRatio": true,
      "layer": "",
      "name": "UpgradePrice",
      "persistentUuid": "315aef63-2b60-4efe-ba66-16d1b3add531",
      "width": 0,
      "x": 617,
      "y": 704,
      "zOrder": 10,
      "numberProperties": [],
      "stringProperties": [],
      "initialVariables": [
        {
          "name": "Upgrade",
          "type": "string",
          "value": "ProjectileSpeed"
        }
      ]
    },
    {
      "angle": 0,
      "customSize": true,
      "depth": 1.044776119402985,
      "height": 70,
      "keepRatio": true,
      "layer": "",
      "name": "UpgradeIcon",
      "persistentUuid": "d77c640b-db15-4b9d-95d3-612b43c2f397",
      "width": 70,
      "x": 25,
      "y": 778,
      "zOrder": 6,
      "numberProperties": [],
      "stringProperties": [],
      "initialVariables": [
        {
          "name": "Upgrade",
          "type": "string",
          "value": "Speed"
        }
      ]
    },
    {
      "angle": 0,
      "customSize": false,
      "height": 0,
      "keepRatio": true,
      "layer": "",
      "name": "UpgradeName",
      "persistentUuid": "eb825e41-3d3a-4438-b6e4-74cac69c9678",
      "width": 0,
      "x": 219,
      "y": 804,
      "zOrder": 8,
      "numberProperties": [],
      "stringProperties": [],
      "initialVariables": [
        {
          "name": "Upgrade",
          "type": "string",
          "value": "Speed"
        }
      ]
    },
    {
      "angle": 0,
      "customSize": false,
      "height": 0,
      "keepRatio": true,
      "layer": "",
      "name": "UpgradeLevel",
      "persistentUuid": "bbed5f91-8e9a-4ac5-bf70-e156b423dde5",
      "width": 0,
      "x": 130,
      "y": 804,
      "zOrder": 9,
      "numberProperties": [],
      "stringProperties": [],
      "initialVariables": [
        {
          "name": "Upgrade",
          "type": "string",
          "value": "Speed"
        }
      ]
    },
    {
      "angle": 0,
      "customSize": false,
      "height": 0,
      "keepRatio": true,
      "layer": "",
      "name": "UpgradePrice",
      "persistentUuid": "02285a5f-21af-4c20-b956-87dfa369c514",
      "width": 0,
      "x": 617,
      "y": 804,
      "zOrder": 10,
      "numberProperties": [],
      "stringProperties": [],
      "initialVariables": [
        {
          "name": "Upgrade",
          "type": "string",
          "value": "Speed"
        }
      ]
    },
    {
      "angle": 0,
      "customSize": true,
      "depth": 1.044776119402985,
      "height": 70,
      "keepRatio": true,
      "layer": "",
      "name": "UpgradeIcon",
      "persistentUuid": "4eaee82f-dae2-42d6-9b48-11147969bbac",
      "width": 70,
      "x": 27,
      "y": 873,
      "zOrder": 6,
      "numberProperties": [],
      "stringProperties": [],
      "initialVariables": [
        {
          "name": "Upgrade",
          "type": "string",
          "value": "TwinCannons"
        }
      ]
    },
    {
      "angle": 0,
      "customSize": false,
      "height": 0,
      "keepRatio": true,
      "layer": "",
      "name": "UpgradeName",
      "persistentUuid": "08cc09b6-3495-435a-b1ab-da5be726e78b",
      "width": 0,
      "x": 221,
      "y": 899,
      "zOrder": 8,
      "numberProperties": [],
      "stringProperties": [],
      "initialVariables": [
        {
          "name": "Upgrade",
          "type": "string",
          "value": "TwinCannons"
        }
      ]
    },
    {
      "angle": 0,
      "customSize": false,
      "height": 0,
      "keepRatio": true,
      "layer": "",
      "name": "UpgradeLevel",
      "persistentUuid": "b8e46e41-e994-4a00-92b9-8b9b29ad2d03",
      "width": 0,
      "x": 132,
      "y": 899,
      "zOrder": 9,
      "numberProperties": [],
      "stringProperties": [],
      "initialVariables": [
        {
          "name": "Upgrade",
          "type": "string",
          "value": "TwinCannons"
        }
      ]
    },
    {
      "angle": 0,
      "customSize": false,
      "height": 0,
      "keepRatio": true,
      "layer": "",
      "name": "UpgradePrice",
      "persistentUuid": "a26e2f82-3453-4ad1-8cac-bfdd0da478dc",
      "width": 0,
      "x": 619,
      "y": 899,
      "zOrder": 10,
      "numberProperties": [],
      "stringProperties": [],
      "initialVariables": [
        {
          "name": "Upgrade",
          "type": "string",
          "value": "Speed"
        }
      ]
    },
    {
      "angle": 0,
      "customSize": true,
      "depth": 0,
      "height": 70.00000000000001,
      "keepRatio": true,
      "layer": "",
      "name": "BuyButton",
      "persistentUuid": "5aed55af-dac5-428c-8f98-5c7c01c27431",
      "width": 70,
      "x": 534,
      "y": 183,
      "zOrder": 11,
      "numberProperties": [],
      "stringProperties": [],
      "initialVariables": [
        {
          "name": "Upgrade",
          "type": "string",
          "value": "ChromaSpread"
        }
      ]
    },
    {
      "angle": 0,
      "customSize": true,
      "depth": 0,
      "height": 70.00000000000001,
      "keepRatio": true,
      "layer": "",
      "name": "BuyButton",
      "persistentUuid": "c9d9e216-b4e9-4e6d-a5e7-1c1c039cc7da",
      "width": 70,
      "x": 536,
      "y": 283,
      "zOrder": 11,
      "numberProperties": [],
      "stringProperties": [],
      "initialVariables": [
        {
          "name": "Upgrade",
          "type": "string",
          "value": "DamageRock"
        }
      ]
    },
    {
      "angle": 0,
      "customSize": true,
      "depth": 0,
      "height": 70.00000000000001,
      "keepRatio": true,
      "layer": "",
      "name": "BuyButton",
      "persistentUuid": "b32e5eef-82a2-48d5-829a-a60f3a855352",
      "width": 70,
      "x": 535,
      "y": 388,
      "zOrder": 11,
      "numberProperties": [],
      "stringProperties": [],
      "initialVariables": [
        {
          "name": "Upgrade",
          "type": "string",
          "value": "FireRate"
        }
      ]
    },
    {
      "angle": 0,
      "customSize": true,
      "depth": 0,
      "height": 70.00000000000001,
      "keepRatio": true,
      "layer": "",
      "name": "BuyButton",
      "persistentUuid": "21401ac7-331b-4ec3-af4d-d16dc1c65f64",
      "width": 70,
      "x": 536,
      "y": 483,
      "zOrder": 11,
      "numberProperties": [],
      "stringProperties": [],
      "initialVariables": [
        {
          "name": "Upgrade",
          "type": "string",
          "value": "Health"
        }
      ]
    },
    {
      "angle": 0,
      "customSize": true,
      "depth": 0,
      "height": 70.00000000000001,
      "keepRatio": true,
      "layer": "",
      "name": "BuyButton",
      "persistentUuid": "d9debbb0-bb09-4cbf-9fdf-98cec101478c",
      "width": 70,
      "x": 534,
      "y": 583,
      "zOrder": 11,
      "numberProperties": [],
      "stringProperties": [],
      "initialVariables": [
        {
          "name": "Upgrade",
          "type": "string",
          "value": "PlayerDamage"
        }
      ]
    },
    {
      "angle": 0,
      "customSize": true,
      "depth": 0,
      "height": 70.00000000000001,
      "keepRatio": true,
      "layer": "",
      "name": "BuyButton",
      "persistentUuid": "d1b6a512-355f-4738-97b4-99f340fd11f1",
      "width": 70,
      "x": 536,
      "y": 683,
      "zOrder": 11,
      "numberProperties": [],
      "stringProperties": [],
      "initialVariables": [
        {
          "name": "Upgrade",
          "type": "string",
          "value": "ProjectileSpeed"
        }
      ]
    },
    {
      "angle": 0,
      "customSize": true,
      "depth": 0,
      "height": 70.00000000000001,
      "keepRatio": true,
      "layer": "",
      "name": "BuyButton",
      "persistentUuid": "0df18426-0f74-4ffc-8fa8-d4ed3a848351",
      "width": 70,
      "x": 535,
      "y": 787,
      "zOrder": 11,
      "numberProperties": [],
      "stringProperties": [],
      "initialVariables": [
        {
          "name": "Upgrade",
          "type": "string",
          "value": "Speed"
        }
      ]
    },
    {
      "angle": 0,
      "customSize": true,
      "depth": 0,
      "height": 70.00000000000001,
      "keepRatio": true,
      "layer": "",
      "name": "BuyButton",
      "persistentUuid": "55ee8711-5193-480e-b235-c88ca04e0fa0",
      "width": 70,
      "x": 537,
      "y": 879,
      "zOrder": 11,
      "numberProperties": [],
      "stringProperties": [],
      "initialVariables": [
        {
          "name": "Upgrade",
          "type": "string",
          "value": "TwinCannons"
        }
      ]
    }
  ],
  "objects": [
    {
      "assetStoreId": "",
      "bold": false,
      "italic": false,
      "name": "Title",
      "smoothed": true,
      "type": "TextObject::Text",
      "underlined": false,
      "variables": [],
      "effects": [],
      "behaviors": [],
      "string": "Upgrades",
      "font": "assets/Fonts/Pixel NES.otf",
      "textAlignment": "center",
      "characterSize": 90,
      "color": {
        "b": 0,
        "g": 0,
        "r": 0
      },
      "content": {
        "bold": false,
        "isOutlineEnabled": false,
        "isShadowEnabled": false,
        "italic": false,
        "outlineColor": "255;255;255",
        "outlineThickness": 2,
        "shadowAngle": 90,
        "shadowBlurRadius": 2,
        "shadowColor": "0;0;0",
        "shadowDistance": 4,
        "shadowOpacity": 127,
        "smoothed": true,
        "underlined": false,
        "text": "Upgrades",
        "font": "assets/Fonts/Pixel NES.otf",
        "textAlignment": "center",
        "verticalTextAlignment": "center",
        "characterSize": 90,
        "color": "0;0;0"
      }
    },
    {
      "assetStoreId": "26f7912e497fefccd32817a0c24533c9304633b47c6e556065dc498219877e81",
      "name": "ReadyButton",
      "type": "PanelSpriteButton::PanelSpriteButton",
      "variant": "",
      "variables": [],
      "effects": [],
      "behaviors": [],
      "content": {
        "LeftPadding": 0,
        "RightPadding": 0,
        "PressedLabelOffsetY": 1,
        "BottomPadding": 0,
        "TopPadding": 0,
        "HoveredFadeOutDuration": 0.2
      },
      "childrenContent": {
        "Hovered": {
          "bottomMargin": 6,
          "height": 64,
          "leftMargin": 6,
          "rightMargin": 6,
          "texture": "On Screen Controls Button_Hovered.png",
          "tiled": false,
          "topMargin": 6,
          "width": 192
        },
        "Idle": {
          "bottomMargin": 6,
          "height": 64,
          "leftMargin": 6,
          "rightMargin": 6,
          "texture": "On Screen Controls Button_Idle.png",
          "tiled": false,
          "topMargin": 6,
          "width": 192
        },
        "Label": {
          "bold": false,
          "italic": false,
          "smoothed": true,
          "underlined": false,
          "string": "Ready",
          "font": "assets/Fonts/Pixel NES.otf",
          "textAlignment": "center",
          "characterSize": 40,
          "color": {
            "b": 255,
            "g": 255,
            "r": 255
          },
          "content": {
            "bold": false,
            "isOutlineEnabled": false,
            "isShadowEnabled": false,
            "italic": false,
            "outlineColor": "255;255;255",
            "outlineThickness": 2,
            "shadowAngle": 90,
            "shadowBlurRadius": 2,
            "shadowColor": "0;0;0",
            "shadowDistance": 4,
            "shadowOpacity": 127,
            "smoothed": true,
            "underlined": false,
            "text": "Ready",
            "font": "assets/Fonts/Pixel NES.otf",
            "textAlignment": "center",
            "verticalTextAlignment": "top",
            "characterSize": 40,
            "color": "255;255;255"
          }
        },
        "Pressed": {
          "bottomMargin": 6,
          "height": 64,
          "leftMargin": 6,
          "rightMargin": 6,
          "texture": "On Screen Controls Button_Pressed.png",
          "tiled": false,
          "topMargin": 6,
          "width": 192
        }
      }
    },
    {
      "assetStoreId": "26f7912e497fefccd32817a0c24533c9304633b47c6e556065dc498219877e81",
      "name": "DebugAddMoney",
      "type": "PanelSpriteButton::PanelSpriteButton",
      "variant": "",
      "variables": [],
      "effects": [],
      "behaviors": [],
      "content": {
        "LeftPadding": 0,
        "RightPadding": 0,
        "PressedLabelOffsetY": 1,
        "BottomPadding": 0,
        "TopPadding": 0,
        "HoveredFadeOutDuration": 0.2
      },
      "childrenContent": {
        "Hovered": {
          "bottomMargin": 6,
          "height": 64,
          "leftMargin": 6,
          "rightMargin": 6,
          "texture": "On Screen Controls Button_Hovered.png",
          "tiled": false,
          "topMargin": 6,
          "width": 192
        },
        "Idle": {
          "bottomMargin": 6,
          "height": 64,
          "leftMargin": 6,
          "rightMargin": 6,
          "texture": "On Screen Controls Button_Idle.png",
          "tiled": false,
          "topMargin": 6,
          "width": 192
        },
        "Label": {
          "bold": false,
          "italic": false,
          "smoothed": true,
          "underlined": false,
          "string": "+",
          "font": "Roboto-Bold.ttf",
          "textAlignment": "center",
          "characterSize": 40,
          "color": {
            "b": 255,
            "g": 255,
            "r": 255
          },
          "content": {
            "bold": false,
            "isOutlineEnabled": false,
            "isShadowEnabled": false,
            "italic": false,
            "outlineColor": "255;255;255",
            "outlineThickness": 2,
            "shadowAngle": 90,
            "shadowBlurRadius": 2,
            "shadowColor": "0;0;0",
            "shadowDistance": 4,
            "shadowOpacity": 127,
            "smoothed": true,
            "underlined": false,
            "text": "+",
            "font": "Roboto-Bold.ttf",
            "textAlignment": "center",
            "verticalTextAlignment": "top",
            "characterSize": 40,
            "color": "255;255;255"
          }
        },
        "Pressed": {
          "bottomMargin": 6,
          "height": 64,
          "leftMargin": 6,
          "rightMargin": 6,
          "texture": "On Screen Controls Button_Pressed.png",
          "tiled": false,
          "topMargin": 6,
          "width": 192
        }
      }
    },
    {
      "assetStoreId": "26f7912e497fefccd32817a0c24533c9304633b47c6e556065dc498219877e81",
      "name": "DebugRemoveMoney",
      "type": "PanelSpriteButton::PanelSpriteButton",
      "variant": "",
      "variables": [],
      "effects": [],
      "behaviors": [],
      "content": {
        "LeftPadding": 0,
        "RightPadding": 0,
        "PressedLabelOffsetY": 1,
        "BottomPadding": 0,
        "TopPadding": 0,
        "HoveredFadeOutDuration": 0.2
      },
      "childrenContent": {
        "Hovered": {
          "bottomMargin": 6,
          "height": 64,
          "leftMargin": 6,
          "rightMargin": 6,
          "texture": "On Screen Controls Button_Hovered.png",
          "tiled": false,
          "topMargin": 6,
          "width": 192
        },
        "Idle": {
          "bottomMargin": 6,
          "height": 64,
          "leftMargin": 6,
          "rightMargin": 6,
          "texture": "On Screen Controls Button_Idle.png",
          "tiled": false,
          "topMargin": 6,
          "width": 192
        },
        "Label": {
          "bold": false,
          "italic": false,
          "smoothed": true,
          "underlined": false,
          "string": "-",
          "font": "Roboto-Bold.ttf",
          "textAlignment": "center",
          "characterSize": 40,
          "color": {
            "b": 255,
            "g": 255,
            "r": 255
          },
          "content": {
            "bold": false,
            "isOutlineEnabled": false,
            "isShadowEnabled": false,
            "italic": false,
            "outlineColor": "255;255;255",
            "outlineThickness": 2,
            "shadowAngle": 90,
            "shadowBlurRadius": 2,
            "shadowColor": "0;0;0",
            "shadowDistance": 4,
            "shadowOpacity": 127,
            "smoothed": true,
            "underlined": false,
            "text": "-",
            "font": "Roboto-Bold.ttf",
            "textAlignment": "center",
            "verticalTextAlignment": "top",
            "characterSize": 40,
            "color": "255;255;255"
          }
        },
        "Pressed": {
          "bottomMargin": 6,
          "height": 64,
          "leftMargin": 6,
          "rightMargin": 6,
          "texture": "On Screen Controls Button_Pressed.png",
          "tiled": false,
          "topMargin": 6,
          "width": 192
        }
      }
    },
    {
      "assetStoreId": "",
      "bold": false,
      "italic": false,
      "name": "UpgradeLevel",
      "smoothed": true,
      "type": "TextObject::Text",
      "underlined": false,
      "variables": [
        {
          "name": "Upgrade",
          "type": "string",
          "value": "ChromaSpread"
        }
      ],
      "effects": [],
      "behaviors": [],
      "string": "1/10",
      "font": "assets/Fonts/VCR_OSD_MONO.ttf",
      "textAlignment": "right",
      "characterSize": 32,
      "color": {
        "b": 0,
        "g": 0,
        "r": 0
      },
      "content": {
        "bold": false,
        "isOutlineEnabled": false,
        "isShadowEnabled": false,
        "italic": false,
        "outlineColor": "255;255;255",
        "outlineThickness": 2,
        "shadowAngle": 90,
        "shadowBlurRadius": 2,
        "shadowColor": "0;0;0",
        "shadowDistance": 4,
        "shadowOpacity": 127,
        "smoothed": true,
        "underlined": false,
        "text": "1/10",
        "font": "assets/Fonts/VCR_OSD_MONO.ttf",
        "textAlignment": "right",
        "verticalTextAlignment": "top",
        "characterSize": 32,
        "color": "0;0;0"
      }
    },
    {
      "assetStoreId": "",
      "bold": false,
      "italic": false,
      "name": "UpgradeName",
      "smoothed": true,
      "type": "TextObject::Text",
      "underlined": false,
      "variables": [
        {
          "name": "Upgrade",
          "type": "string",
          "value": "ChromaSpread"
        }
      ],
      "effects": [],
      "behaviors": [],
      "string": "Anti-Asteroid",
      "font": "assets/Fonts/VCR_OSD_MONO.ttf",
      "textAlignment": "left",
      "characterSize": 32,
      "color": {
        "b": 0,
        "g": 0,
        "r": 0
      },
      "content": {
        "bold": false,
        "isOutlineEnabled": false,
        "isShadowEnabled": false,
        "italic": false,
        "outlineColor": "255;255;255",
        "outlineThickness": 2,
        "shadowAngle": 90,
        "shadowBlurRadius": 2,
        "shadowColor": "0;0;0",
        "shadowDistance": 4,
        "shadowOpacity": 127,
        "smoothed": true,
        "underlined": false,
        "text": "Anti-Asteroid",
        "font": "assets/Fonts/VCR_OSD_MONO.ttf",
        "textAlignment": "left",
        "verticalTextAlignment": "top",
        "characterSize": 32,
        "color": "0;0;0"
      }
    },
    {
      "assetStoreId": "",
      "bold": false,
      "italic": false,
      "name": "UpgradePrice",
      "smoothed": true,
      "type": "TextObject::Text",
      "underlined": false,
      "variables": [
        {
          "name": "Upgrade",
          "type": "string",
          "value": "ChromaSpread"
        }
      ],
      "effects": [],
      "behaviors": [],
      "string": "100",
      "font": "assets/Fonts/VCR_OSD_MONO.ttf",
      "textAlignment": "left",
      "characterSize": 32,
      "color": {
        "b": 0,
        "g": 0,
        "r": 0
      },
      "content": {
        "bold": false,
        "isOutlineEnabled": false,
        "isShadowEnabled": false,
        "italic": false,
        "outlineColor": "255;255;255",
        "outlineThickness": 2,
        "shadowAngle": 90,
        "shadowBlurRadius": 2,
        "shadowColor": "0;0;0",
        "shadowDistance": 4,
        "shadowOpacity": 127,
        "smoothed": true,
        "underlined": false,
        "text": "100",
        "font": "assets/Fonts/VCR_OSD_MONO.ttf",
        "textAlignment": "left",
        "verticalTextAlignment": "top",
        "characterSize": 32,
        "color": "0;0;0"
      }
    },
    {
      "adaptCollisionMaskAutomatically": true,
      "assetStoreId": "",
      "name": "BuyButton",
      "type": "Sprite",
      "updateIfNotVisible": false,
      "variables": [
        {
          "name": "Upgrade",
          "type": "string",
          "value": "0"
        },
        {
          "name": "Cost",
          "type": "number",
          "value": 0
        }
      ],
      "effects": [],
      "behaviors": [
        {
          "name": "ButtonFSM",
          "type": "ButtonStates::ButtonFSM",
          "ShouldCheckHovering": true,
          "State": "Idle",
          "TouchId": 0,
          "TouchIsInside": false,
          "MouseIsInside": false,
          "Index": 2.0247e-320
        }
      ],
      "animations": [
        {
          "name": "CanBuy",
          "useMultipleDirections": false,
          "directions": [
            {
              "looping": false,
              "timeBetweenFrames": 0.08,
              "sprites": [
                {
                  "hasCustomCollisionMask": true,
                  "image": "assets\\UI\\icon_buy.png",
                  "points": [],
                  "originPoint": {
                    "name": "origine",
                    "x": 0,
                    "y": 0
                  },
                  "centerPoint": {
                    "automatic": true,
                    "name": "centre",
                    "x": 0,
                    "y": 0
                  },
                  "customCollisionMask": [
                    [
                      {
                        "x": 9,
                        "y": 9
                      },
                      {
                        "x": 192,
                        "y": 9
                      },
                      {
                        "x": 192,
                        "y": 180
                      },
                      {
                        "x": 9,
                        "y": 180
                      }
                    ]
                  ]
                }
              ]
            }
          ]
        },
        {
          "name": "NoBuy",
          "useMultipleDirections": false,
          "directions": [
            {
              "looping": false,
              "timeBetweenFrames": 0.08,
              "sprites": [
                {
                  "hasCustomCollisionMask": true,
                  "image": "assets\\UI\\icon_nobuy.png",
                  "points": [],
                  "originPoint": {
                    "name": "origine",
                    "x": 0,
                    "y": 0
                  },
                  "centerPoint": {
                    "automatic": true,
                    "name": "centre",
                    "x": 0,
                    "y": 0
                  },
                  "customCollisionMask": [
                    [
                      {
                        "x": 9,
                        "y": 9
                      },
                      {
                        "x": 192,
                        "y": 9
                      },
                      {
                        "x": 192,
                        "y": 180
                      },
                      {
                        "x": 9,
                        "y": 180
                      }
                    ]
                  ]
                }
              ]
            }
          ]
        }
      ]
    }
  ],
  "objectsFolderStructure": {
    "folderName": "__ROOT",
    "children": [
      {
        "objectName": "Title"
      },
      {
        "objectName": "ReadyButton"
      },
      {
        "objectName": "DebugAddMoney"
      },
      {
        "objectName": "DebugRemoveMoney"
      },
      {
        "objectName": "UpgradeLevel"
      },
      {
        "objectName": "UpgradePrice"
      },
      {
        "objectName": "UpgradeName"
      },
      {
        "objectName": "BuyButton"
      }
    ]
  },
  "events": [
    {
      "type": "BuiltinCommonInstructions::Standard",
      "conditions": [
        {
          "type": {
            "value": "DepartScene"
          },
          "parameters": [
            ""
          ]
        }
      ],
      "actions": [
        {
          "type": {
            "value": "ReadNumberFromStorage"
          },
          "parameters": [
            "\"Save\"",
            "\"Currency\"",
            "",
            "CurrencyTemp"
          ]
        },
        {
          "type": {
            "value": "SetNumberVariable"
          },
          "parameters": [
            "Currency",
            "=",
            "CurrencyTemp"
          ]
        }
      ],
      "events": [
        {
          "type": "BuiltinCommonInstructions::Standard",
          "conditions": [
            {
              "type": {
                "value": "GroupExists"
              },
              "parameters": [
                "\"Save\"",
                "\"Upgrades\""
              ]
            }
          ],
          "actions": [
            {
              "type": {
                "value": "ReadStringFromStorage"
              },
              "parameters": [
                "\"Save\"",
                "\"Upgrades\"",
                "",
                "TempUpgrades"
              ]
            },
            {
              "type": {
                "value": "JSONToVariableStructure2"
              },
              "parameters": [
                "TempUpgrades",
                "UpgradeLevels"
              ]
            }
          ]
        },
        {
          "type": "BuiltinCommonInstructions::Standard",
          "conditions": [],
          "actions": []
        }
      ]
    },
    {
      "colorB": 228,
      "colorG": 176,
      "colorR": 74,
      "creationTime": 0,
      "folded": true,
      "name": "Debug",
      "source": "",
      "type": "BuiltinCommonInstructions::Group",
      "events": [
        {
          "type": "BuiltinCommonInstructions::Standard",
          "conditions": [
            {
              "type": {
                "value": "PanelSpriteButton::PanelSpriteButton::IsPressed"
              },
              "parameters": [
                "DebugAddMoney",
                ""
              ]
            }
          ],
          "actions": [
            {
              "type": {
                "value": "SetNumberVariable"
              },
              "parameters": [
                "Currency",
                "+",
                "1"
              ]
            }
          ]
        },
        {
          "type": "BuiltinCommonInstructions::Standard",
          "conditions": [
            {
              "type": {
                "value": "PanelSpriteButton::PanelSpriteButton::IsPressed"
              },
              "parameters": [
                "DebugRemoveMoney",
                ""
              ]
            }
          ],
          "actions": [
            {
              "type": {
                "value": "SetNumberVariable"
              },
              "parameters": [
                "Currency",
                "=",
                "max(0, Currency- 1)"
              ]
            }
          ]
        }
      ],
      "parameters": []
    },
    {
      "type": "BuiltinCommonInstructions::Standard",
      "conditions": [
        {
          "type": {
            "value": "NumberObjectVariable"
          },
          "parameters": [
            "CurrencyDisplay",
            "CurrentCurrency",
            "!=",
            "Currency"
          ]
        }
      ],
      "actions": [
        {
          "type": {
            "value": "TextContainerCapability::TextContainerBehavior::SetValue"
          },
          "parameters": [
            "CurrencyDisplay",
            "Text",
            "=",
            "\"$\" + Currency"
          ]
        },
        {
          "type": {
            "value": "SetNumberObjectVariable"
          },
          "parameters": [
            "CurrencyDisplay",
            "CurrentCurrency",
            "=",
            "Currency"
          ]
        }
      ]
    },
    {
      "type": "BuiltinCommonInstructions::Standard",
      "conditions": [
        {
          "type": {
            "value": "PanelSpriteButton::PanelSpriteButton::IsPressed"
          },
          "parameters": [
            "ReadyButton",
            ""
          ]
        }
      ],
      "actions": [
        {
          "type": {
            "value": "EcrireFichierExp"
          },
          "parameters": [
            "\"Save\"",
            "\"Currency\"",
            "Currency"
          ]
        },
        {
          "type": {
            "value": "EcrireFichierTxt"
          },
          "parameters": [
            "\"Save\"",
            "\"Upgrades\"",
            "ToJSON(UpgradeLevels)"
          ]
        }
      ],
      "events": [
        {
          "type": "BuiltinCommonInstructions::Standard",
          "conditions": [],
          "actions": [
            {
              "type": {
                "value": "Scene"
              },
              "parameters": [
                "",
                "\"gameplay\"",
                ""
              ]
            }
          ]
        }
      ]
    },
    {
      "type": "BuiltinCommonInstructions::Standard",
      "conditions": [
        {
          "type": {
            "value": "NumberVariable"
          },
          "parameters": [
            "LastUpdatedCurrency",
            "!=",
            "Currency"
          ]
        }
      ],
      "actions": [
        {
          "type": {
            "value": "SetNumberVariable"
          },
          "parameters": [
            "LastUpdatedCurrency",
            "=",
            "Currency"
          ]
        }
      ],
      "events": [
        {
          "type": "BuiltinCommonInstructions::Standard",
          "conditions": [],
          "actions": [
            {
              "type": {
                "value": "AnimatableCapability::AnimatableBehavior::SetName"
              },
              "parameters": [
                "UpgradeIcon",
                "Animation",
                "=",
                "UpgradeIcon.Upgrade"
              ]
            },
            {
              "type": {
                "value": "TextContainerCapability::TextContainerBehavior::SetValue"
              },
              "parameters": [
                "UpgradeName",
                "Text",
                "=",
                "IkaRuleGa::GetUpgradeName(UpgradeName.Upgrade)"
              ]
            },
            {
              "type": {
                "value": "TextContainerCapability::TextContainerBehavior::SetValue"
              },
              "parameters": [
                "UpgradeLevel",
                "Text",
                "=",
                "ToString(UpgradeLevels[UpgradeLevel.Upgrade]) + \"/\" + ToString(IkaRuleGa::GetUpgradeMaxRank(UpgradeLevel.Upgrade))"
              ]
            },
            {
              "type": {
                "value": "TextContainerCapability::TextContainerBehavior::SetValue"
              },
              "parameters": [
                "UpgradePrice",
                "Text",
                "=",
                "ToString(IkaRuleGa::GetNextRankCost(UpgradePrice.Upgrade, UpgradeLevels[UpgradePrice.Upgrade]))"
              ]
            },
            {
              "type": {
                "value": "SetNumberObjectVariable"
              },
              "parameters": [
                "BuyButton",
                "Cost",
                "=",
                "IkaRuleGa::GetNextRankCost(BuyButton.Upgrade, UpgradeLevels[BuyButton.Upgrade])"
              ]
            },
            {
              "type": {
                "value": "SetNumberObjectVariable"
              },
              "parameters": [
                "BuyButton",
                "Cost",
                "=",
                "IkaRuleGa::GetNextRankCost(BuyButton.Upgrade, UpgradeLevels[BuyButton.Upgrade])"
              ]
            }
          ],
          "events": [
            {
              "type": "BuiltinCommonInstructions::ForEach",
              "object": "BuyButton",
              "conditions": [],
              "actions": [],
              "events": [
                {
                  "type": "BuiltinCommonInstructions::Standard",
                  "conditions": [
                    {
                      "type": {
                        "value": "NumberObjectVariable"
                      },
                      "parameters": [
                        "BuyButton",
                        "Cost",
                        "<=",
                        "Currency"
                      ]
                    }
                  ],
                  "actions": [
                    {
                      "type": {
                        "value": "AnimatableCapability::AnimatableBehavior::SetName"
                      },
                      "parameters": [
                        "BuyButton",
                        "Animation",
                        "=",
                        "\"CanBuy\""
                      ]
                    }
                  ]
                },
                {
                  "type": "BuiltinCommonInstructions::Standard",
                  "conditions": [
                    {
                      "type": {
                        "value": "NumberObjectVariable"
                      },
                      "parameters": [
                        "BuyButton",
                        "Cost",
                        ">",
                        "Currency"
                      ]
                    }
                  ],
                  "actions": [
                    {
                      "type": {
                        "value": "AnimatableCapability::AnimatableBehavior::SetName"
                      },
                      "parameters": [
                        "BuyButton",
                        "Animation",
                        "=",
                        "\"NoBuy\""
                      ]
                    }
                  ]
                }
              ]
            }
          ]
        }
      ]
    },
    {
      "type": "BuiltinCommonInstructions::Standard",
      "conditions": [
        {
          "type": {
            "value": "ButtonStates::ButtonFSM::IsClicked"
          },
          "parameters": [
            "BuyButton",
            "ButtonFSM",
            ""
          ]
        },
        {
          "type": {
            "value": "AnimatableCapability::AnimatableBehavior::Name"
          },
          "parameters": [
            "BuyButton",
            "Animation",
            "=",
            "\"CanBuy\""
          ]
        }
      ],
      "actions": [],
      "events": [
        {
          "type": "BuiltinCommonInstructions::Standard",
          "conditions": [],
          "actions": [
            {
              "type": {
                "value": "SetNumberVariable"
              },
              "parameters": [
                "Currency",
                "=",
                "Currency - IkaRuleGa::GetNextRankCost(BuyButton.Upgrade, UpgradeLevels[BuyButton.Upgrade])"
              ]
            },
            {
              "type": {
                "value": "SetNumberVariable"
              },
              "parameters": [
                "UpgradeLevels[BuyButton.Upgrade]",
                "=",
                "UpgradeLevels[BuyButton.Upgrade] + 1"
              ]
            }
          ]
        }
      ]
    },
    {
      "type": "BuiltinCommonInstructions::Standard",
      "conditions": [],
      "actions": []
    }
  ],
  "layers": [
    {
      "ambientLightColorB": 200,
      "ambientLightColorG": 200,
      "ambientLightColorR": 200,
      "camera3DFarPlaneDistance": 10000,
      "camera3DFieldOfView": 45,
      "camera3DNearPlaneDistance": 3,
      "cameraType": "",
      "followBaseLayerCamera": false,
      "isLightingLayer": false,
      "isLocked": false,
      "name": "",
      "renderingType": "",
      "visibility": true,
      "cameras": [
        {
          "defaultSize": true,
          "defaultViewport": true,
          "height": 0,
          "viewportBottom": 1,
          "viewportLeft": 0,
          "viewportRight": 1,
          "viewportTop": 0,
          "width": 0
        }
      ],
      "effects": [
        {
          "effectType": "Scene3D::HemisphereLight",
          "name": "3D Light",
          "doubleParameters": {
            "elevation": 45,
            "intensity": 1,
            "rotation": 0
          },
          "stringParameters": {
            "groundColor": "64;64;64",
            "skyColor": "255;255;255",
            "top": "Y-"
          },
          "booleanParameters": {}
        }
      ]
    }
  ],
  "behaviorsSharedData": [
    {
      "name": "Animation",
      "type": "AnimatableCapability::AnimatableBehavior"
    },
    {
      "name": "ButtonFSM",
      "type": "ButtonStates::ButtonFSM"
    },
    {
      "name": "Effect",
      "type": "EffectCapability::EffectBehavior"
    },
    {
      "name": "Flippable",
      "type": "FlippableCapability::FlippableBehavior"
    },
    {
      "name": "Opacity",
      "type": "OpacityCapability::OpacityBehavior"
    },
    {
      "name": "Resizable",
      "type": "ResizableCapability::ResizableBehavior"
    },
    {
      "name": "Scale",
      "type": "ScalableCapability::ScalableBehavior"
    },
    {
      "name": "Text",
      "type": "TextContainerCapability::TextContainerBehavior"
    }
  ]
}